pickfun/__init__.py
pickfun/pickfun.py
pickfun-0.1.0.dist-info/WHEEL
pickfun-0.1.0.dist-info/METADATA
pickfun-0.1.0.dist-info/RECORD
